LICENSE.md
README.md
setup.py
game/__init__.py
game/helper_methods.py
game/runner.py
game/controller/__init__.py
game/controller/activator_controller.py
game/controller/dungeon_controller.py
game/controller/save_controller.py
game/data/__init__.py
game/data/logo.txt
game/data/save.json
game/data/scenario.json
game/data/scenario_texts.py
game/data/texts.py
game/data/__pycache__/__init__.cpython-39.pyc
game/data/__pycache__/scenario_texts.cpython-39.pyc
game/data/__pycache__/texts.cpython-39.pyc
game/model/__init__.py
game/model/activator.py
game/model/animate.py
game/model/chest.py
game/model/door.py
game/model/element.py
game/model/food.py
game/model/location.py
game/model/player.py
game/model/rope.py
game/model/thing.py
game/model/tool.py
game/model/enums/__init__.py
game/model/enums/activator_type.py
game/view/__init__.py
game/view/console_view.py
hemonaluto.egg-info/PKG-INFO
hemonaluto.egg-info/SOURCES.txt
hemonaluto.egg-info/dependency_links.txt
hemonaluto.egg-info/entry_points.txt
hemonaluto.egg-info/requires.txt
hemonaluto.egg-info/top_level.txt
scripts/__init__.py
scripts/generate_test_world.py
scripts/generate_world.py
scripts/../game/data/__init__.py
scripts/../game/data/logo.txt
scripts/../game/data/save.json
scripts/../game/data/scenario.json
scripts/../game/data/scenario_texts.py
scripts/../game/data/texts.py
scripts/../game/data/__pycache__/__init__.cpython-39.pyc
scripts/../game/data/__pycache__/scenario_texts.cpython-39.pyc
scripts/../game/data/__pycache__/texts.cpython-39.pyc
tests/__init__.py
tests/test_activator_handler.py
tests/test_dungeon_master.py
tests/test_load.py
tests/../game/data/__init__.py
tests/../game/data/logo.txt
tests/../game/data/save.json
tests/../game/data/scenario.json
tests/../game/data/scenario_texts.py
tests/../game/data/texts.py
tests/../game/data/__pycache__/__init__.cpython-39.pyc
tests/../game/data/__pycache__/scenario_texts.cpython-39.pyc
tests/../game/data/__pycache__/texts.cpython-39.pyc