Metadata-Version: 2.1
Name: hemonaluto
Version: 0.0.1
Summary: A text adventure game!
Home-page: https://github.com/gasupidupi/Hemonaluto
Author: Gabriel Schafflützel
Author-email: schaffluetzel.gabriel@gmail.com
License: GNU General Public License v3.0
Keywords: text-based adventure game
Classifier: Development Status :: 2 - Pre-Alpha
Classifier: Topic :: Games/Entertainment
Classifier: Environment :: Console
Classifier: Programming Language :: Python :: 3.9
Classifier: License :: OSI Approved :: GNU General Public License v3 (GPLv3)
Requires-Python: >=3.8
License-File: LICENSE.md
